check_rkn/__init__.py
check_rkn/check_rkn.py
check_rkn-1.2.1.dist-info/METADATA
check_rkn-1.2.1.dist-info/WHEEL
check_rkn-1.2.1.dist-info/licenses/LICENSE
check_rkn-1.2.1.dist-info/licenses/NOTICE
check_rkn-1.2.1.dist-info/RECORD
