Metadata-Version: 2.4
Name: check-rkn
Version: 1.2.1
Summary: Library that check blocked website on blocklist.rkn.gov.ru
Project-URL: Repository, https://codeberg.org/IvanyaK/check-rkn
Author-email: IvanyaK <ivanrus200519@gmail.com>
License-Expression: Apache-2.0
License-File: LICENSE
License-File: NOTICE
Requires-Python: ~=3.10
Requires-Dist: anticaptchaofficial<2,>=1.0.53
Requires-Dist: selenium<5,>=4.10.0
